dobu_manager/__init__.py
dobu_manager/app.py
dobu_manager/config.py
dobu_manager/example_config.yaml
dobu_manager/lifespan.py
dobu_manager/main.py
dobu_manager/registry.py
dobu_manager/controllers/__init__.py
dobu_manager/controllers/node_controller.py
dobu_manager/controllers/optuna_controller.py
dobu_manager/controllers/study_controller.py
dobu_manager/repositories/__init__.py
dobu_manager/repositories/node_repository.py
dobu_manager/repositories/study_repository.py
dobu_manager/services/__init__.py
dobu_manager/services/codebase_service.py
dobu_manager/services/node_service.py
dobu_manager/services/study_service.py
dobu_manager/services/zip_service.py
executor/__init__.py
executor/main.py
executor/requests.py
executor/rest_storage.py
koko_worker/__init__.py
koko_worker/cluster.py
koko_worker/config.py
koko_worker/download.py
koko_worker/environment.py
koko_worker/example_config.json
koko_worker/import_utils.py
koko_worker/main.py
koko_worker/pinger.py
koko_worker/requests.py
shared/__init__.py
shared/models/__init__.py
shared/models/node.py
shared/models/optuna.py
shared/models/study.py
kodu_optim-0.1.2.dist-info/METADATA
kodu_optim-0.1.2.dist-info/WHEEL
kodu_optim-0.1.2.dist-info/entry_points.txt
kodu_optim-0.1.2.dist-info/RECORD
