Metadata-Version: 2.4
Name: kodu_optim
Version: 0.1.2
Summary: A distributed optimization package
Author-email: Vincent Verbergt <vincent.verbergt@gmail.com>
Requires-Python: >=3.13
Requires-Dist: aiohttp>=3.11.16
Requires-Dist: fastapi[standard]>=0.115.12
Requires-Dist: filelock>=3.18.0
Requires-Dist: loguru>=0.7.3
Requires-Dist: optuna-dashboard>=0.18.0
Requires-Dist: optuna>=4.2.1
Requires-Dist: psutil>=7.0.0
Requires-Dist: psycopg2-binary>=2.9.10
Requires-Dist: python-multipart>=0.0.20
Requires-Dist: tinydb>=4.8.2
